nunchaku_installer/__init__.py
nunchaku_installer/cli.py
nunchaku_installer/detector.py
nunchaku_installer/github.py
nunchaku_installer/logic.py
nunchaku_installer-0.1.0.dist-info/licenses/LICENSE
nunchaku_installer-0.1.0.dist-info/METADATA
nunchaku_installer-0.1.0.dist-info/WHEEL
nunchaku_installer-0.1.0.dist-info/entry_points.txt
nunchaku_installer-0.1.0.dist-info/top_level.txt
nunchaku_installer-0.1.0.dist-info/RECORD
