Metadata-Version: 2.4
Name: nunchaku-installer
Version: 0.1.0
Summary: A simple installer to download and install the Nunchaku library from GitHub Releases.
Author: Juste-Leo
License-Expression: MIT
Project-URL: Homepage, https://github.com/Juste-Leo2/nunchaku-installer
Project-URL: Bug Tracker, https://github.com/Juste-Leo2/nunchaku-installer/issues
Classifier: Programming Language :: Python :: 3
Classifier: Operating System :: OS Independent
Classifier: Topic :: Software Development :: Build Tools
Classifier: Topic :: System :: Archiving :: Packaging
Requires-Python: >=3.8
License-File: LICENSE
Requires-Dist: typer
Requires-Dist: packaging
Dynamic: license-file
